Workbook

Sheet Portada
B3: PADEL PALMIRA CLUB DEPORTIVO
B5: Reporte Financiero para Inversionistas
B6: Análisis Operativo y Estado de Resultados Ajustado · Noviembre 2024 – Mayo 2026
B12: Ubicación | G12: Confidencialidad
B13: Av. Palmira No. 58, Cuernavaca, Morelos, México | G13: Este documento contiene información financiera confidencial preparada exclusivamente para inversionistas potenciales evaluando la adquisición de Padel Palmira Club Deportivo. Prohibida su distribución sin autorización.
B15: Instalaciones
B16: 3 canchas techadas · terreno de 3,762 m² (uso de suelo permite alberca, cancha de tenis y casa club)
B18: Periodo analizado
B19: 19 meses de operación (Nov 2024 – May 2026)
B22: Contenido del Reporte
B24: 1. Resumen Ejecutivo — KPIs clave y tesis de inversión
B25: 2. Notas Metodológicas — ajustes aplicados a los estados financieros originales
B26: 3. P&L Operativo Ajustado — estado de resultados mensual, 19 meses
B27: 4. Desglose de Ingresos por Categoría
B28: 5. Estructura de Costos Operativos
B29: 6. Márgenes por Categoría
B30: 7. Tendencias Mensuales — estacionalidad y evolución
... B38: padelpalmira@gmail.com · Único canal de contacto para esta oportunidad

Sheet Resumen Ejecutivo
B2: Resumen Ejecutivo
B3: Cifras operativas ajustadas · Últimos 12 meses (Jun 2025 – May 2026) salvo que se indique lo contrario
B5: Ingresos Operativos (TTM) | E5: EBITDA Operativo Ajustado (TTM) | H5: Margen EBITDA (TTM) | K5: Crecimiento Ingresos (vs. primeros 7 meses)
B6: =SUM('P&L Operativo Ajustado'!J7:U7) -> 2507416.7 | E6: =SUM('P&L Operativo Ajustado'!J38:U38) -> 1088577.3 | H6: =SUM('P&L Operativo Ajustado'!J38:U38)/SUM('P&L Operativo Ajustado'!J7:U7) -> 0.43414296 | K6: =(AVERAGE('P&L Operativo Ajustado'!J7:U7)/AVERAGE('P&L Operativo Ajustado'!C7:I7))-1 -> 0.37822183
B9: Ingreso Mensual Promedio (TTM) | E9: EBITDA Mensual Promedio (TTM) | H9: Precio de Venta Solicitado | K9: Múltiplo EBITDA (Precio / EBITDA TTM)
B10: =AVERAGE('P&L Operativo Ajustado'!J7:U7) -> 208951.39 | E10: =AVERAGE('P&L Operativo Ajustado'!J38:U38) -> 90714.777 | H10: 33000000 | K10: =H10/SUM('P&L Operativo Ajustado'!J38:U38) -> 30.314797
B13: Nota: el múltiplo EBITDA es alto en términos de negocio operativo porque el precio de $33M incluye el valor del terreno de 3,762 m² (Av. Palmira 58) — ver Estudio de Valuación Inmobiliaria para el desglose separado de valor de tierra vs. negocio.
B14: Tesis de Inversión
B16: • Negocio operando 19 meses con EBITDA operativo positivo desde el primer mes registrado.
B17: • Ingresos diversificados: cancha (~54%), academia (~22%) y consumo (bebidas, cafetería, botana, pelotas, grips ~24%).
B18: • Modelo de academia con comisión 50% a entrenadores reduce riesgo de costo fijo docente.
B19: • Terreno de 3,762 m², con alberca, cancha de tenis y casa club sin activar — upside de expansión sin comprar más tierra ni tramitar cambio de uso de suelo.
B20: • Oportunidad de crecimiento clara: horarios matutinos (8am–12pm) con baja ocupación y mercado femenino desatendido.
B21: • Ubicación en Av. Palmira, zona comercial de alto poder adquisitivo en Cuernavaca.
B22: • Estructura de costos transparente: se excluyeron gastos personales y compensación del dueño saliente para reflejar el costo real de operación bajo nueva administración.
B23: • Proyección de crecimiento orgánico a 3 años disponible en la hoja "Proyecciones" — escenario conservador, excluye Fase 2.
B25: Nota: cifras ajustadas — excluyen gastos personales de los socios, Fondo Apapacho (recaudación benéfica de terceros) y el sueldo del Director General saliente. Ver "Notas Metodológicas".

Sheet Notas Metodológicas
B2: Notas Metodológicas y Ajustes Aplicados
B3: Diferencias entre el estado de resultados original y el estado de resultados operativo ajustado presentado en este reporte
B5: Ajuste | C5: Explicación y tratamiento aplicado
B6: Fondo Apapacho (recaudación anticáncer) | C6: Se identificó que este monto se registraba simultáneamente como ingreso y como egreso por el mismo valor (venta de pelotas rosas y activaciones cuya recaudación se entrega íntegra a una fundación contra el cáncer). No es ingreso ni gasto operativo del club: se excluyó de ambos lados del estado de resultados ajustado.
B7: Sueldo Director General | C7: Corresponde a la compensación del propietario actual, quien no continuará en el proyecto tras la venta. Se excluye del EBITDA operativo ajustado por no ser un costo recurrente para el comprador. Se mantiene el "Sueldo Gerente" (gerente contratado) como costo operativo real, ya que ese rol sí permanece.
B8: Gastos Personales de los socios | C8: Retiros y gastos personales de los socios (rentas de vivienda, alimentación, transporte, viajes, compras personales) identificados dentro de la contabilidad del club. Se excluyeron del estado de resultados operativo. Incluye la partida "Renta" registrada en 2024–2025 (renta de vivienda personal, no del terreno del club — la renta del terreno es prácticamente nula por ser propiedad familiar), "Alimentación" y "Transporte TAG/Gasolina".
B9: Repartición de utilidades entre socios | C9: Retiros de efectivo documentados en una bitácora separada (depósitos para vivienda, viajes) que nunca formaron parte del estado de resultados operativo del club. Se excluyen por completo de este reporte por tratarse de movimientos patrimoniales entre los socios, no operación del negocio.
B10: Descuadre de caja (efectivo real vs. utilidad teórica acumulada) | C10: Al comparar el efectivo real en cuentas y caja contra la utilidad acumulada que se desprende de los registros (neta de retiros de socios), el efectivo real resulta MAYOR en todos los cortes disponibles, por entre $25,000 y $106,000 MXN. No hay faltante de efectivo. La explicación más probable es de calendario: los saldos se tomaron en fechas intermedias del mes, antes de liquidar nómina, comisiones de entrenadores y gastos de cierre; también es posible un saldo inicial previo a noviembre 2024. Pendiente de confirmar con el propietario y el contador. Un comprador institucional deberá establecer cortes de caja a fin de mes.
B11: Corrección de errores de fórmula | C11: La fila "Suma Utilidad" (utilidad acumulada) del archivo original contenía referencias rotas en varios meses. Se corrigió y se recalculó de forma consistente en este reporte.
B12: Margen EBITDA ajustado (43.4%) — por qué es superior a la industria | C12: El margen es superior al promedio de la industria (25-35%) porque el terreno es propiedad familiar y no se paga renta de mercado; esa condición se mantiene para el comprador, ya que el terreno se vende junto con el negocio. La nómina también es ligera (2 recepcionistas, 1 gerente; los entrenadores cobran por comisión). No incluye depreciación ni una reserva de mantenimiento de largo plazo — ver Estados_Financieros_Padel_Palmira.xlsx para utilidad de operación, ISR pro forma y flujo libre.
B14: Fórmula: EBITDA Operativo Ajustado = (Ingresos totales − Fondo Apapacho) − (Egresos totales − Fondo Apapacho − Sueldo Director General − Gastos Personales). Los gastos personales se excluyen una sola vez: no forman parte de las líneas de egreso de la hoja P&L.

Sheet P&L Operativo Ajustado
B2: Estado de Resultados Operativo Ajustado
B3: Excluye: Fondo Apapacho (pass-through), Sueldo Director General (no recurrente post-venta), y gastos personales reclasificados. Ver hoja "Notas Metodológicas".
B6: Concepto | C6: Nov-24 | D6: Dic-24 | E6: Ene-25 | F6: Feb-25 | G6: Mar-25 | H6: Abr-25 | I6: May-25 | J6: Jun-25 | K6: Jul-25 | L6: Ago-25 | M6: Sep-25 | N6: Oct-25 | O6: Nov-25 | P6: Dic-25 | Q6: Ene-26 | R6: Feb-26 | S6: Mar-26 | T6: Abr-26 | U6: May-26
B7: INGRESOS OPERATIVOS | C7: =SUM('Datos Fuente'!C8:C15) -> 121118.85 | D7: =SUM('Datos Fuente'!D8:D15) -> 122328 | E7: =SUM('Datos Fuente'!E8:E15) -> 132050 | F7: =SUM('Datos Fuente'!F8:F15) -> 152941 | G7: =SUM('Datos Fuente'!G8:G15) -> 175195 | H7: =SUM('Datos Fuente'!H8:H15) -> 192060 | I7: =SUM('Datos Fuente'!I8:I15) -> 165573 | J7: =SUM('Datos Fuente'!J8:J15) -> 193376 | ... U7: =SUM('Datos Fuente'!U8:U15) -> 207796.07
B8: Cancha | C8: ='Datos Fuente'!C8 -> 81741.85 | D8: ='Datos Fuente'!D8 -> 95495 | E8: ='Datos Fuente'!E8 -> 99567 | F8: ='Datos Fuente'!F8 -> 93620 | G8: ='Datos Fuente'!G8 -> 109082 | H8: ='Datos Fuente'!H8 -> 120527 | I8: ='Datos Fuente'!I8 -> 101404 | J8: ='Datos Fuente'!J8 -> 113871 | ... U8: ='Datos Fuente'!U8 -> 102242
B9: Clases | C9: ='Datos Fuente'!C9 -> 17000 | D9: ='Datos Fuente'!D9 -> 2400 | E9: ='Datos Fuente'!E9 -> 13200 | F9: ='Datos Fuente'!F9 -> 31200 | G9: ='Datos Fuente'!G9 -> 26500 | H9: ='Datos Fuente'!H9 -> 30400 | I9: ='Datos Fuente'!I9 -> 26600 | J9: ='Datos Fuente'!J9 -> 36350 | ... U9: ='Datos Fuente'!U9 -> 63700
B10: Bebidas | C10: ='Datos Fuente'!C10 -> 11020 | D10: ='Datos Fuente'!D10 -> 11936 | E10: ='Datos Fuente'!E10 -> 10435 | F10: ='Datos Fuente'!F10 -> 12510 | G10: ='Datos Fuente'!G10 -> 15730 | H10: ='Datos Fuente'!H10 -> 15405 | I10: ='Datos Fuente'!I10 -> 15320 | J10: ='Datos Fuente'!J10 -> 12260 | ... U10: ='Datos Fuente'!U10 -> 19507.36
B11: Pelotas | C11: ='Datos Fuente'!C11 -> 6247 | D11: ='Datos Fuente'!D11 -> 5237 | E11: ='Datos Fuente'!E11 -> 3918 | F11: ='Datos Fuente'!F11 -> 3146 | G11: ='Datos Fuente'!G11 -> 9858 | H11: ='Datos Fuente'!H11 -> 12248 | I11: ='Datos Fuente'!I11 -> 7884 | J11: ='Datos Fuente'!J11 -> 12870 | ... U11: ='Datos Fuente'!U11 -> 10159.64
B12: Cafetería | C12: ='Datos Fuente'!C12 -> 0 | D12: ='Datos Fuente'!D12 -> 0 | E12: ='Datos Fuente'!E12 -> 0 | F12: ='Datos Fuente'!F12 -> 5905 | G12: ='Datos Fuente'!G12 -> 6950 | H12: ='Datos Fuente'!H12 -> 6010 | I12: ='Datos Fuente'!I12 -> 7860 | J12: ='Datos Fuente'!J12 -> 10720 | ... U12: ='Datos Fuente'!U12 -> 6024.64
B13: Botana | C13: ='Datos Fuente'!C13 -> 2585 | D13: ='Datos Fuente'!D13 -> 2875 | E13: ='Datos Fuente'!E13 -> 2750 | F13: ='Datos Fuente'!F13 -> 2845 | G13: ='Datos Fuente'!G13 -> 3160 | H13: ='Datos Fuente'!H13 -> 3350 | I13: ='Datos Fuente'!I13 -> 3675 | J13: ='Datos Fuente'!J13 -> 4775 | ... U13: ='Datos Fuente'!U13 -> 4197.43
B14: Grips y Palas | C14: ='Datos Fuente'!C14 -> 2525 | D14: ='Datos Fuente'!D14 -> 4385 | E14: ='Datos Fuente'!E14 -> 2180 | F14: ='Datos Fuente'!F14 -> 3715 | G14: ='Datos Fuente'!G14 -> 3915 | H14: ='Datos Fuente'!H14 -> 4120 | I14: ='Datos Fuente'!I14 -> 2830 | J14: ='Datos Fuente'!J14 -> 2530 | ... U14: ='Datos Fuente'!U14 -> 1965
B15: Sacos | C15: ='Datos Fuente'!C15 -> 0 | D15: ='Datos Fuente'!D15 -> 0 | E15: ='Datos Fuente'!E15 -> 0 | F15: ='Datos Fuente'!F15 -> 0 | G15: ='Datos Fuente'!G15 -> 0 | H15: ='Datos Fuente'!H15 -> 0 | I15: ='Datos Fuente'!I15 -> 0 | J15: ='Datos Fuente'!J15 -> 0 | ... U15: ='Datos Fuente'!U15 -> 0
B17: EGRESOS OPERATIVOS | C17: ='Datos Fuente'!C19+'Datos Fuente'!C20+'Datos Fuente'!C21+'Datos Fuente'!C22+'Datos Fuente'!C23+'Datos Fuente'!C24+'Datos Fuente'!C25+'Datos Fuente'!C27+'Datos Fuente'!C28+'Datos Fuente'!C29+'Datos Fuente'!C30+'Datos Fuente'!C31+'Datos Fuente'!C32+'Datos Fuente'!C33+'Datos Fuente'!C34+'Datos Fuente'!C35+'Datos Fuente'!C36 -> 69866.26 | D17: ='Datos Fuente'!D19+'Datos Fuente'!D20+'Datos Fuente'!D21+'Datos Fuente'!D22+'Datos Fuente'!D23+'Datos Fuente'!D24+'Datos Fuente'!D25+'Datos Fuente'!D27+'Datos Fuente'!D28+'Datos Fuente'!D29+'Datos Fuente'!D30+'Datos Fuente'!D31+'Datos Fuente'!D32+'Datos Fuente'!D33+'Datos Fuente'!D34+'Datos Fuente'!D35+'Datos Fuente'!D36 -> 70283.43 | E17: ='Datos Fuente'!E19+'Datos Fuente'!E20+'Datos Fuente'!E21+'Datos Fuente'!E22+'Datos Fuente'!E23+'Datos Fuente'!E24+'Datos Fuente'!E25+'Datos Fuente'!E27+'Datos Fuente'!E28+'Datos Fuente'!E29+'Datos Fuente'!E30+'Datos Fuente'!E31+'Datos Fuente'!E32+'Datos Fuente'!E33+'Datos Fuente'!E34+'Datos Fuente'!E35+'Datos Fuente'!E36 -> 61744 | F17: ='Datos Fuente'!F19+'Datos Fuente'!F20+'Datos Fuente'!F21+'Datos Fuente'!F22+'Datos Fuente'!F23+'Datos Fuente'!F24+'Datos Fuente'!F25+'Datos Fuente'!F27+'Datos Fuente'!F28+'Datos Fuente'!F29+'Datos Fuente'!F30+'Datos Fuente'!F31+'Datos Fuente'!F32+'Datos Fuente'!F33+'Datos Fuente'!F34+'Datos Fuente'!F35+'Datos Fuente'!F36 -> 97791 | G17: ='Datos Fuente'!G19+'Datos Fuente'!G20+'Datos Fuente'!G21+'Datos Fuente'!G22+'Datos Fuente'!G23+'Datos Fuente'!G24+'Datos Fuente'!G25+'Datos Fuente'!G27+'Datos Fuente'!G28+'Datos Fuente'!G29+'Datos Fuente'!G30+'Datos Fuente'!G31+'Datos Fuente'!G32+'Datos Fuente'!G33+'Datos Fuente'!G34+'Datos Fuente'!G35+'Datos Fuente'!G36 -> 85287 | H17: ='Datos Fuente'!H19+'Datos Fuente'!H20+'Datos Fuente'!H21+'Datos Fuente'!H22+'Datos Fuente'!H23+'Datos Fuente'!H24+'Datos Fuente'!H25+'Datos Fuente'!H27+'Datos Fuente'!H28+'Datos Fuente'!H29+'Datos Fuente'!H30+'Datos Fuente'!H31+'Datos Fuente'!H32+'Datos Fuente'!H33+'Datos Fuente'!H34+'Datos Fuente'!H35+'Datos Fuente'!H36 -> 108268 | I17: ='Datos Fuente'!I19+'Datos Fuente'!I20+'Datos Fuente'!I21+'Datos Fuente'!I22+'Datos Fuente'!I23+'Datos Fuente'!I24+'Datos Fuente'!I25+'Datos Fuente'!I27+'Datos Fuente'!I28+'Datos Fuente'!I29+'Datos Fuente'!I30+'Datos Fuente'!I31+'Datos Fuente'!I32+'Datos Fuente'!I33+'Datos Fuente'!I34+'Datos Fuente'!I35+'Datos Fuente'!I36 -> 117575 | J17: ='Datos Fuente'!J19+'Datos Fuente'!J20+'Datos Fuente'!J21+'Datos Fuente'!J22+'Datos Fuente'!J23+'Datos Fuente'!J24+'Datos Fuente'!J25+'Datos Fuente'!J27+'Datos Fuente'!J28+'Datos Fuente'!J29+'Datos Fuente'!J30+'Datos Fuente'!J31+'Datos Fuente'!J32+'Datos Fuente'!J33+'Datos Fuente'!J34+'Datos Fuente'!J35+'Datos Fuente'!J36 -> 104841.5 | ... U17: ='Datos Fuente'!U19+'Datos Fuente'!U20+'Datos Fuente'!U21+'Datos Fuente'!U22+'Datos Fuente'!U23+'Datos Fuente'!U24+'Datos Fuente'!U25+'Datos Fuente'!U27+'Datos Fuente'!U28+'Datos Fuente'!U29+'Datos Fuente'!U30+'Datos Fuente'!U31+'Datos Fuente'!U32+'Datos Fuente'!U33+'Datos Fuente'!U34+'Datos Fuente'!U35+'Datos Fuente'!U36 -> 115858
B18: Abogado | C18: ='Datos Fuente'!C19 -> 0 | D18: ='Datos Fuente'!D19 -> 0 | E18: ='Datos Fuente'!E19 -> 0 | F18: ='Datos Fuente'!F19 -> 0 | G18: ='Datos Fuente'!G19 -> 0 | H18: ='Datos Fuente'!H19 -> 0 | I18: ='Datos Fuente'!I19 -> 0 | J18: ='Datos Fuente'!J19 -> 0 | ... U18: ='Datos Fuente'!U19 -> 0
B19: Bono Empleados | C19: ='Datos Fuente'!C20 -> 0 | D19: ='Datos Fuente'!D20 -> 0 | E19: ='Datos Fuente'!E20 -> 0 | F19: ='Datos Fuente'!F20 -> 0 | G19: ='Datos Fuente'!G20 -> 0 | H19: ='Datos Fuente'!H20 -> 0 | I19: ='Datos Fuente'!I20 -> 0 | J19: ='Datos Fuente'!J20 -> 0 | ... U19: ='Datos Fuente'!U20 -> 500
B20: Cambio Vidrios | C20: ='Datos Fuente'!C21 -> 0 | D20: ='Datos Fuente'!D21 -> 18800 | E20: ='Datos Fuente'!E21 -> 0 | F20: ='Datos Fuente'!F21 -> 0 | G20: ='Datos Fuente'!G21 -> 0 | H20: ='Datos Fuente'!H21 -> 19080 | I20: ='Datos Fuente'!I21 -> 31080 | J20: ='Datos Fuente'!J21 -> 0 | ... U20: ='Datos Fuente'!U21 -> 0
B21: Contador | C21: ='Datos Fuente'!C22 -> 0 | D21: ='Datos Fuente'!D22 -> 0 | E21: ='Datos Fuente'!E22 -> 0 | F21: ='Datos Fuente'!F22 -> 0 | G21: ='Datos Fuente'!G22 -> 0 | H21: ='Datos Fuente'!H22 -> 0 | I21: ='Datos Fuente'!I22 -> 0 | J21: ='Datos Fuente'!J22 -> 5220 | ... U21: ='Datos Fuente'!U22 -> 6960
B22: Costo Limpieza Vidrios | C22: ='Datos Fuente'!C23 -> 0 | D22: ='Datos Fuente'!D23 -> 2160 | E22: ='Datos Fuente'!E23 -> 2340 | F22: ='Datos Fuente'!F23 -> 2160 | G22: ='Datos Fuente'!G23 -> 2340 | H22: ='Datos Fuente'!H23 -> 2340 | I22: ='Datos Fuente'!I23 -> 2340 | J22: ='Datos Fuente'!J23 -> 2340 | ... U22: ='Datos Fuente'!U23 -> 0
B23: Costos Inventario | C23: ='Datos Fuente'!C24 -> 11305.26 | D23: ='Datos Fuente'!D24 -> 10793.43 | E23: ='Datos Fuente'!E24 -> 9633 | F23: ='Datos Fuente'!F24 -> 19758 | G23: ='Datos Fuente'!G24 -> 19792 | H23: ='Datos Fuente'!H24 -> 19784 | I23: ='Datos Fuente'!I24 -> 17203 | J23: ='Datos Fuente'!J24 -> 21260 | ... U23: ='Datos Fuente'!U24 -> 22888
B24: Empleados | C24: ='Datos Fuente'!C25 -> 17000 | D24: ='Datos Fuente'!D25 -> 17000 | E24: ='Datos Fuente'!E25 -> 17000 | F24: ='Datos Fuente'!F25 -> 27000 | G24: ='Datos Fuente'!G25 -> 28900 | H24: ='Datos Fuente'!H25 -> 27000 | I24: ='Datos Fuente'!I25 -> 29500 | J24: ='Datos Fuente'!J25 -> 18500 | ... U24: ='Datos Fuente'!U25 -> 21750
B25: Gastos Generales | C25: ='Datos Fuente'!C27 -> 6543 | D25: ='Datos Fuente'!D27 -> 6689 | E25: ='Datos Fuente'!E27 -> 10604 | F25: ='Datos Fuente'!F27 -> 28190 | G25: ='Datos Fuente'!G27 -> 21448 | H25: ='Datos Fuente'!H27 -> 17261 | I25: ='Datos Fuente'!I27 -> 19838 | J25: ='Datos Fuente'!J27 -> 14760 | ... U25: ='Datos Fuente'!U27 -> 0
B26: Insumos Cafeteria | C26: ='Datos Fuente'!C28 -> 0 | D26: ='Datos Fuente'!D28 -> 0 | E26: ='Datos Fuente'!E28 -> 0 | F26: ='Datos Fuente'!F28 -> 0 | G26: ='Datos Fuente'!G28 -> 0 | H26: ='Datos Fuente'!H28 -> 0 | I26: ='Datos Fuente'!I28 -> 0 | J26: ='Datos Fuente'!J28 -> 0 | ... U26: ='Datos Fuente'!U28 -> 3113
B27: Limpieza general | C27: ='Datos Fuente'!C29 -> 2800 | D27: ='Datos Fuente'!D29 -> 2700 | E27: ='Datos Fuente'!E29 -> 2800 | F27: ='Datos Fuente'!F29 -> 2800 | G27: ='Datos Fuente'!G29 -> 2800 | H27: ='Datos Fuente'!H29 -> 2800 | I27: ='Datos Fuente'!I29 -> 3150 | J27: ='Datos Fuente'!J29 -> 2800 | ... U27: ='Datos Fuente'!U29 -> 2340
B28: Mantenimiento | C28: ='Datos Fuente'!C30 -> 16753 | D28: ='Datos Fuente'!D30 -> 4780 | E28: ='Datos Fuente'!E30 -> 11540 | F28: ='Datos Fuente'!F30 -> 5731 | G28: ='Datos Fuente'!G30 -> 0 | H28: ='Datos Fuente'!H30 -> 539 | I28: ='Datos Fuente'!I30 -> 1400 | J28: ='Datos Fuente'!J30 -> 9000 | ... U28: ='Datos Fuente'!U30 -> 5221
B29: Mejoras | C29: ='Datos Fuente'!C31 -> 0 | D29: ='Datos Fuente'!D31 -> 0 | E29: ='Datos Fuente'!E31 -> 0 | F29: ='Datos Fuente'!F31 -> 0 | G29: ='Datos Fuente'!G31 -> 0 | H29: ='Datos Fuente'!H31 -> 0 | I29: ='Datos Fuente'!I31 -> 0 | J29: ='Datos Fuente'!J31 -> 0 | ... U29: ='Datos Fuente'!U31 -> 0
B30: Merchandise | C30: ='Datos Fuente'!C32 -> 0 | D30: ='Datos Fuente'!D32 -> 0 | E30: ='Datos Fuente'!E32 -> 0 | F30: ='Datos Fuente'!F32 -> 0 | G30: ='Datos Fuente'!G32 -> 0 | H30: ='Datos Fuente'!H32 -> 0 | I30: ='Datos Fuente'!I32 -> 0 | J30: ='Datos Fuente'!J32 -> 0 | ... U30: ='Datos Fuente'!U32 -> 0
B31: Profesor | C31: ='Datos Fuente'!C33 -> 11900 | D31: ='Datos Fuente'!D33 -> 792 | E31: ='Datos Fuente'!E33 -> 4356 | F31: ='Datos Fuente'!F33 -> 10296 | G31: ='Datos Fuente'!G33 -> 8745 | H31: ='Datos Fuente'!H33 -> 10032 | I31: ='Datos Fuente'!I33 -> 8778 | J31: ='Datos Fuente'!J33 -> 11995.5 | ... U31: ='Datos Fuente'!U33 -> 35541
B32: Publicidad | C32: ='Datos Fuente'!C34 -> 0 | D32: ='Datos Fuente'!D34 -> 0 | E32: ='Datos Fuente'!E34 -> 0 | F32: ='Datos Fuente'!F34 -> 0 | G32: ='Datos Fuente'!G34 -> 0 | H32: ='Datos Fuente'!H34 -> 0 | I32: ='Datos Fuente'!I34 -> 0 | J32: ='Datos Fuente'!J34 -> 0 | ... U32: ='Datos Fuente'!U34 -> 0
B33: Servicios | C33: ='Datos Fuente'!C35 -> 3565 | D33: ='Datos Fuente'!D35 -> 6569 | E33: ='Datos Fuente'!E35 -> 3471 | F33: ='Datos Fuente'!F35 -> 1856 | G33: ='Datos Fuente'!G35 -> 1262 | H33: ='Datos Fuente'!H35 -> 9432 | I33: ='Datos Fuente'!I35 -> 4286 | J33: ='Datos Fuente'!J35 -> 18966 | ... U33: ='Datos Fuente'!U35 -> 1675
B34: Sueldo Gerente | C34: ='Datos Fuente'!C36 -> 0 | D34: ='Datos Fuente'!D36 -> 0 | E34: ='Datos Fuente'!E36 -> 0 | F34: ='Datos Fuente'!F36 -> 0 | G34: ='Datos Fuente'!G36 -> 0 | H34: ='Datos Fuente'!H36 -> 0 | I34: ='Datos Fuente'!I36 -> 0 | J34: ='Datos Fuente'!J36 -> 0 | ... U34: ='Datos Fuente'!U36 -> 15870
B35: Memo: Renta / Alimentación / Transporte personales 2024-25 (excluidos — no forman parte de las líneas anteriores ni del total) | C35: ='Datos Fuente'!C40+'Datos Fuente'!C41+'Datos Fuente'!C42 -> 26149 | D35: ='Datos Fuente'!D40+'Datos Fuente'!D41+'Datos Fuente'!D42 -> 30765 | E35: ='Datos Fuente'!E40+'Datos Fuente'!E41+'Datos Fuente'!E42 -> 28109 | F35: ='Datos Fuente'!F40+'Datos Fuente'!F41+'Datos Fuente'!F42 -> 23752 | G35: ='Datos Fuente'!G40+'Datos Fuente'!G41+'Datos Fuente'!G42 -> 28815 | H35: ='Datos Fuente'!H40+'Datos Fuente'!H41+'Datos Fuente'!H42 -> 33225 | I35: ='Datos Fuente'!I40+'Datos Fuente'!I41+'Datos Fuente'!I42 -> 35691 | J35: ='Datos Fuente'!J40+'Datos Fuente'!J41+'Datos Fuente'!J42 -> 28119 | ... U35: ='Datos Fuente'!U40+'Datos Fuente'!U41+'Datos Fuente'!U42 -> 0
B36: Sueldo Director General (registrado, NO contabilizado en EBITDA — sueldo del dueño saliente) | C36: ='Datos Fuente'!C37 -> 0 | D36: ='Datos Fuente'!D37 -> 0 | E36: ='Datos Fuente'!E37 -> 0 | F36: ='Datos Fuente'!F37 -> 0 | G36: ='Datos Fuente'!G37 -> 0 | H36: ='Datos Fuente'!H37 -> 0 | I36: ='Datos Fuente'!I37 -> 0 | J36: ='Datos Fuente'!J37 -> 0 | ... U36: ='Datos Fuente'!U37 -> 40000
B38: EBITDA OPERATIVO AJUSTADO | C38: =C7-C17 -> 51252.59 | D38: =D7-D17 -> 52044.57 | E38: =E7-E17 -> 70306 | F38: =F7-F17 -> 55150 | G38: =G7-G17 -> 89908 | H38: =H7-H17 -> 83792 | I38: =I7-I17 -> 47998 | J38: =J7-J17 -> 88534.5 | ... U38: =U7-U17 -> 91938.07
B39: Margen EBITDA % | C39: =C38/C7 -> 0.42315948 | D39: =D38/D7 -> 0.425451 | E39: =E38/E7 -> 0.53241954 | F39: =F38/F7 -> 0.36059657 | G39: =G38/G7 -> 0.51318816 | H39: =H38/H7 -> 0.43628033 | I39: =I38/I7 -> 0.28989026 | J39: =J38/J7 -> 0.45783603 | ... U39: =U38/U7 -> 0.44244374
B41: PARTIDAS EXCLUIDAS (referencia, no afectan EBITDA operativo)
B42: Fondo Apapacho (neutral, excluido de ambos lados) | C42: ='Datos Fuente'!C26 -> 0 | D42: ='Datos Fuente'!D26 -> 0 | E42: ='Datos Fuente'!E26 -> 1110 | F42: ='Datos Fuente'!F26 -> 0 | G42: ='Datos Fuente'!G26 -> 300 | H42: ='Datos Fuente'!H26 -> 0 | I42: ='Datos Fuente'!I26 -> 0 | J42: ='Datos Fuente'!J26 -> 0 | ... U42: ='Datos Fuente'!U26 -> 900

Sheet Desglose de Ingresos
B2: Desglose de Ingresos por Categoría
B3: Acumulado 19 meses (Nov 2024 – May 2026), excluye Fondo Apapacho
B5: Categoría | C5: Ingreso Acumulado | D5: % del Total
B6: Cancha | C6: =SUM('Datos Fuente'!C8:U8) -> 2060853.9 | D6: =C6/C$14 -> 0.5774831
B7: Clases | C7: =SUM('Datos Fuente'!C9:U9) -> 696200 | D7: =C7/C$14 -> 0.195086
B8: Bebidas | C8: =SUM('Datos Fuente'!C10:U10) -> 293135.63 | D8: =C8/C$14 -> 0.082141133
B9: Pelotas | C9: =SUM('Datos Fuente'!C11:U11) -> 197324.57 | D9: =C9/C$14 -> 0.055293393
B10: Cafetería | C10: =SUM('Datos Fuente'!C12:U12) -> 151095.4 | D10: =C10/C$14 -> 0.042339266
B11: Botana | C11: =SUM('Datos Fuente'!C13:U13) -> 103502.4 | D11: =C11/C$14 -> 0.029002972
B12: Grips y Palas | C12: =SUM('Datos Fuente'!C14:U14) -> 63420.71 | D12: =C12/C$14 -> 0.017771463
B13: Sacos | C13: =SUM('Datos Fuente'!C15:U15) -> 3150 | D13: =C13/C$14 -> 0.00088267867
B14: TOTAL | C14: =SUM(C6:C13) -> 3568682.6 | D14: =C14/C$14 -> 1

Sheet Estructura de Costos
B2: Estructura de Costos Operativos
B3: Acumulado 19 meses · excluye Fondo Apapacho, Sueldo Director General y gastos personales reclasificados
B5: Categoría de Gasto | C5: Egreso Acumulado | D5: % del Total
B6: Abogado | C6: =SUM('Datos Fuente'!C19:U19) -> 74851.64 | D6: =C6/C$23 -> 0.036879013
B7: Bono Empleados | C7: =SUM('Datos Fuente'!C20:U20) -> 5890 | D7: =C7/C$23 -> 0.0029019723
B8: Cambio Vidrios | C8: =SUM('Datos Fuente'!C21:U21) -> 68960 | D8: =C8/C$23 -> 0.033976233
B9: Contador | C9: =SUM('Datos Fuente'!C22:U22) -> 55820 | D9: =C9/C$23 -> 0.027502223
B10: Costo Limpieza Vidrios | C10: =SUM('Datos Fuente'!C23:U23) -> 31859.1 | D10: =C10/C$23 -> 0.015696813
B11: Costos Inventario | C11: =SUM('Datos Fuente'!C24:U24) -> 366877.11 | D11: =C11/C$23 -> 0.18075844
B12: Empleados | C12: =SUM('Datos Fuente'!C25:U25) -> 476538 | D12: =C12/C$23 -> 0.23478779
B13: Gastos Generales | C13: =SUM('Datos Fuente'!C27:U27) -> 211907 | D13: =C13/C$23 -> 0.10440547
B14: Insumos Cafeteria | C14: =SUM('Datos Fuente'!C28:U28) -> 27807.8 | D14: =C14/C$23 -> 0.013700758
B15: Limpieza general | C15: =SUM('Datos Fuente'!C29:U29) -> 54260 | D15: =C15/C$23 -> 0.026733619
B16: Mantenimiento | C16: =SUM('Datos Fuente'!C30:U30) -> 123515 | D16: =C16/C$23 -> 0.060855197
B17: Mejoras | C17: =SUM('Datos Fuente'!C31:U31) -> 14713.7 | D17: =C17/C$23 -> 0.0072493633
B18: Merchandise | C18: =SUM('Datos Fuente'!C32:U32) -> 11116 | D18: =C18/C$23 -> 0.0054767953
B19: Profesor | C19: =SUM('Datos Fuente'!C33:U33) -> 304770.75 | D19: =C19/C$23 -> 0.15015896
B20: Publicidad | C20: =SUM('Datos Fuente'!C34:U34) -> 7200 | D20: =C20/C$23 -> 0.0035474025
B21: Servicios | C21: =SUM('Datos Fuente'!C35:U35) -> 146838 | D21: =C21/C$23 -> 0.072346318
B22: Sueldo Gerente | C22: =SUM('Datos Fuente'!C36:U36) -> 46730 | D22: =C22/C$23 -> 0.023023628
B23: TOTAL EGRESOS OPERATIVOS | C23: =SUM(C6:C22) -> 2029654.1 | D23: =C23/C$23 -> 1

Sheet Márgenes por Categoría
B2: Márgenes de Contribución por Categoría (Punto de Venta / Loyverse)
B3: Muestra de un mes representativo (mayo 2026) — ilustra la calidad de margen del mix de ingresos del club
B5: Categoría | C5: Unidades Vendidas | D5: Ventas Netas | E5: Costo de Bienes | F5: Beneficio Bruto | G5: Margen %
B6: Bebidas | C6: 1158 | D6: 33026 | E6: 16113.03 | F6: =D6-E6 -> 16912.97 | G6: =F6/D6 -> 0.51211076
B7: Botanas / Comida | C7: 353 | D7: 7985 | E7: 3882.33 | F7: =D7-E7 -> 4102.67 | G7: =F7/D7 -> 0.51379712
B8: Clases | C8: 33 | D8: 32600 | E8: =D8*(SUM('Datos Fuente'!C33:U33)/SUM('Datos Fuente'!C9:U9)) -> 14271.081 | F8: =D8-E8 -> 18328.919 | G8: =F8/D8 -> 0.56223679
B9: Grips y Palas | C9: 346 | D9: 9150 | E9: 566.86 | F9: =D9-E9 -> 8583.14 | G9: =F9/D9 -> 0.93804809
B10: Hora Cancha | C10: 1146 | D10: 274103 | E10: 0 | F10: =D10-E10 -> 274103 | G10: =F10/D10 -> 1
B11: Pelotas | C11: 259 | D11: 15402 | E11: 10122.64 | F11: =D11-E11 -> 5279.36 | G11: =F11/D11 -> 0.34277107
B12: TOTAL / PROMEDIO PONDERADO | C12: =SUM(C6:C11) -> 3295 | D12: =SUM(D6:D11) -> 372266 | E12: =SUM(E6:E11) -> 44955.941 | F12: =SUM(F6:F11) -> 327310.06 | G12: =F12/D12 -> 0.87923705
B14: Nota: "Hora Cancha" no tiene costo de bienes porque no requiere insumos (costo real: personal/mantenimiento, ya reflejado en gastos operativos). "Clases" se recalculó: Loyverse no registra la comisión al profesor como costo, así que el costo se estimó como el sueldo total de profesores entre el ingreso total de clases de todo el periodo (nov-24 a may-26) — resultando en ~40-55% del ingreso, consistente con lo reportado por el propietario, en vez del 0% original.

Sheet Tendencias Mensuales
B2: Tendencias Mensuales — Ingresos, Egresos, EBITDA y Margen
B5: Concepto | C5: Nov-24 | D5: Dic-24 | E5: Ene-25 | F5: Feb-25 | G5: Mar-25 | H5: Abr-25 | I5: May-25 | J5: Jun-25 | K5: Jul-25 | L5: Ago-25 | M5: Sep-25 | N5: Oct-25 | O5: Nov-25 | P5: Dic-25 | Q5: Ene-26 | R5: Feb-26 | S5: Mar-26 | T5: Abr-26 | U5: May-26
B6: Ingresos Operativos | C6: ='P&L Operativo Ajustado'!C7 -> 121118.85 | D6: ='P&L Operativo Ajustado'!D7 -> 122328 | E6: ='P&L Operativo Ajustado'!E7 -> 132050 | F6: ='P&L Operativo Ajustado'!F7 -> 152941 | G6: ='P&L Operativo Ajustado'!G7 -> 175195 | H6: ='P&L Operativo Ajustado'!H7 -> 192060 | I6: ='P&L Operativo Ajustado'!I7 -> 165573 | J6: ='P&L Operativo Ajustado'!J7 -> 193376 | ... U6: ='P&L Operativo Ajustado'!U7 -> 207796.07
B7: Egresos Operativos | C7: ='P&L Operativo Ajustado'!C17 -> 69866.26 | D7: ='P&L Operativo Ajustado'!D17 -> 70283.43 | E7: ='P&L Operativo Ajustado'!E17 -> 61744 | F7: ='P&L Operativo Ajustado'!F17 -> 97791 | G7: ='P&L Operativo Ajustado'!G17 -> 85287 | H7: ='P&L Operativo Ajustado'!H17 -> 108268 | I7: ='P&L Operativo Ajustado'!I17 -> 117575 | J7: ='P&L Operativo Ajustado'!J17 -> 104841.5 | ... U7: ='P&L Operativo Ajustado'!U17 -> 115858
B8: EBITDA Operativo | C8: ='P&L Operativo Ajustado'!C38 -> 51252.59 | D8: ='P&L Operativo Ajustado'!D38 -> 52044.57 | E8: ='P&L Operativo Ajustado'!E38 -> 70306 | F8: ='P&L Operativo Ajustado'!F38 -> 55150 | G8: ='P&L Operativo Ajustado'!G38 -> 89908 | H8: ='P&L Operativo Ajustado'!H38 -> 83792 | I8: ='P&L Operativo Ajustado'!I38 -> 47998 | J8: ='P&L Operativo Ajustado'!J38 -> 88534.5 | ... U8: ='P&L Operativo Ajustado'!U38 -> 91938.07
B9: Margen EBITDA % | C9: ='P&L Operativo Ajustado'!C39 -> 0.42315948 | D9: ='P&L Operativo Ajustado'!D39 -> 0.425451 | E9: ='P&L Operativo Ajustado'!E39 -> 0.53241954 | F9: ='P&L Operativo Ajustado'!F39 -> 0.36059657 | G9: ='P&L Operativo Ajustado'!G39 -> 0.51318816 | H9: ='P&L Operativo Ajustado'!H39 -> 0.43628033 | I9: ='P&L Operativo Ajustado'!I39 -> 0.28989026 | J9: ='P&L Operativo Ajustado'!J39 -> 0.45783603 | ... U9: ='P&L Operativo Ajustado'!U39 -> 0.44244374

Sheet Proyecciones
B2: Proyecciones Financieras — Escenario Orgánico (Sin Fase 2)
B3: Crecimiento orgánico del negocio actual a 3 años. No incluye la expansión de Fase 2 (alberca, cancha de tenis, casa club, modelo de membresías) — ver documento Operación y Expansión, Sección 7.
B5: Supuestos Clave
B6: Tasa de crecimiento anual aplicada | E6: 0.115
B7: • Fuente de la tasa: crecimiento de horas de cancha ocupadas documentado año contra año (Playtomic, enero–mayo 2026 vs. enero–mayo 2025). Se aplica de forma uniforme a todas las líneas de ingreso, como supuesto conservador y trazable — no se proyectan tasas distintas por categoría.
B8: • Margen EBITDA: se mantiene constante en el nivel actual (43.4%, ver hoja "Resumen Ejecutivo") — no se asumen mejoras de eficiencia operativa adicionales durante el periodo proyectado.
B9: • Excluye Fase 2: la expansión del club (alberca, tenis, casa club, membresías) requiere un estudio de factibilidad dedicado y no está incluida en este escenario. Ver documento "Operación y Expansión", Sección 7, para el detalle cualitativo de esa oportunidad.
B10: • Esta proyección es una estimación basada en tendencia histórica documentada — no constituye una garantía de resultados futuros. Sujeta a validación por el equipo de due diligence del inversionista.
B12: Ingresos y EBITDA Proyectados
B13: Concepto | C13: Año 0 (TTM actual) | D13: Año 1 | E13: Año 2 | F13: Año 3
B14: Ingresos Operativos | C14: =SUM('P&L Operativo Ajustado'!J7:U7) -> 2507416.7 | D14: =C14*(1+$E$6) -> 2795769.7 | E14: =D14*(1+$E$6) -> 3117283.2 | F14: =E14*(1+$E$6) -> 3475770.7
B15: EBITDA Operativo Ajustado | C15: =SUM('P&L Operativo Ajustado'!J38:U38) -> 1088577.3 | D15: =D14*($C$15/$C$14) -> 1213763.7 | E15: =E14*($C$15/$C$14) -> 1353346.5 | F15: =F14*($C$15/$C$14) -> 1508981.4
B16: Margen EBITDA % | C16: =C15/C14 -> 0.43414296 | D16: =D15/D14 -> 0.43414296 | E16: =E15/E14 -> 0.43414296 | F16: =F15/F14 -> 0.43414296
B19: Proyección de Ingresos por Categoría
B20: Concepto | C20: Año 0 (TTM actual) | D20: Año 1 | E20: Año 2 | F20: Año 3
B21: Cancha (incl. Hungers Escaleras) | C21: =SUM('P&L Operativo Ajustado'!J8:U8) -> 1359417 | D21: =C21*(1+$E$6) -> 1515750 | E21: =D21*(1+$E$6) -> 1690061.2 | F21: =E21*(1+$E$6) -> 1884418.3
B22: Academia (Clases) | C22: =SUM('P&L Operativo Ajustado'!J9:U9) -> 548900 | D22: =C22*(1+$E$6) -> 612023.5 | E22: =D22*(1+$E$6) -> 682406.2 | F22: =E22*(1+$E$6) -> 760882.92
B23: Bebidas | C23: =SUM('P&L Operativo Ajustado'!J10:U10) -> 200779.63 | D23: =C23*(1+$E$6) -> 223869.29 | E23: =D23*(1+$E$6) -> 249614.26 | F23: =E23*(1+$E$6) -> 278319.89
B24: Pelotas | C24: =SUM('P&L Operativo Ajustado'!J11:U11) -> 148786.57 | D24: =C24*(1+$E$6) -> 165897.03 | E24: =D24*(1+$E$6) -> 184975.18 | F24: =E24*(1+$E$6) -> 206247.33
B25: Cafetería | C25: =SUM('P&L Operativo Ajustado'!J12:U12) -> 124370.4 | D25: =C25*(1+$E$6) -> 138673 | E25: =D25*(1+$E$6) -> 154620.39 | F25: =E25*(1+$E$6) -> 172401.74
B26: Botana | C26: =SUM('P&L Operativo Ajustado'!J13:U13) -> 82262.4 | D26: =C26*(1+$E$6) -> 91722.576 | E26: =D26*(1+$E$6) -> 102270.67 | F26: =E26*(1+$E$6) -> 114031.8
B27: Grips, Palas y Sacos | C27: =SUM('P&L Operativo Ajustado'!J14:U14)+SUM('P&L Operativo Ajustado'!J15:U15) -> 42900.71 | D27: =C27*(1+$E$6) -> 47834.292 | E27: =D27*(1+$E$6) -> 53335.235 | F27: =E27*(1+$E$6) -> 59468.787
B28: Total | C28: =SUM(C21:C27) -> 2507416.7 | D28: =SUM(D21:D27) -> 2795769.7 | E28: =SUM(E21:E27) -> 3117283.2 | F28: =SUM(F21:F27) -> 3475770.7

Sheet Conciliación de Caja
B2: Conciliación de Caja — Efectivo Real vs. Utilidad Teórica
B3: Incluida para transparencia total con el comprador. En todos los cortes el efectivo real es mayor a la utilidad acumulada según registros neta de retiros (no hay faltante). La diferencia se atribuye principalmente a la fecha de los cortes de saldo (antes de pagos de fin de mes). Pendiente de confirmar con el contador.
B6: Cuenta | C6: May-25 | D6: Jun-25 | E6: Jul-25 | F6: Ago-25 | G6: Sep-25 | H6: Nov-25 | I6: Dic-25 | J6: Ene-26 | K6: Abr-26
B7: Clip | C7: 2600 | D7: 70600 | E7: 18000 | F7: 2404 | G7: 22722 | H7: 5769 | I7: 4851 | J7: 12374 | K7: 111744
B8: BBVA | C8: 37000 | D8: 5200 | E8: 17600 | F8: 14627 | G8: 25796 | H8: 9540 | I8: 20793 | J8: 15500 | K8: 13054
B9: Nu | C9: 130000 | D9: 130000 | E9: 158000 | F9: 134000 | G9: 134283 | H9: 135179 | I9: 136000 | J9: 136000 | K9: 113000
B10: Ualá | C10: 50400 | D10: 50800 | E10: 101000 | F10: 101749 | G10: 102062 | H10: 102443 | I10: 102700 | J10: 102700 | K10: 103000
B11: Didi | C11: 0 | D11: 0 | E11: 0 | F11: 0 | G11: 0 | H11: 25474 | I11: 25800 | J11: 25800 | K11: 26700
B12: Efectivo (caja) | C12: 50000 | D12: 100000 | E12: 105000 | F12: 115000 | G12: 49000 | H12: 118800 | I12: 128000 | J12: 100000 | K12: 100000
B13: Total Efectivo Real | C13: =SUM(C7:C12) -> 270000 | D13: =SUM(D7:D12) -> 356600 | E13: =SUM(E7:E12) -> 399600 | F13: =SUM(F7:F12) -> 367780 | G13: =SUM(G7:G12) -> 333863 | H13: =SUM(H7:H12) -> 397205 | I13: =SUM(I7:I12) -> 418144 | J13: =SUM(J7:J12) -> 392374 | K13: =SUM(K7:K12) -> 467498
B14: Utilidad Teórica Acumulada | C14: 245355.16 | D14: 305770.66 | E14: 376610.66 | F14: 396006.66 | G14: 419164.99 | H14: 486439.99 | I14: 515000 | J14: 531187.38 | K14: 646603.8
B15: Retiros de Efectivo de Socios (acum.) | C15: 0 | D15: 0 | E15: 0 | F15: 64000 | G15: 164000 | H15: 164000 | I15: 202000 | J15: 202000 | K15: 228000
B16: Diferencia: Efectivo real − (Utilidad teórica − Retiros) [positivo = sobra efectivo] | C16: =C13-(C14-C15) -> 24644.84 | D16: =D13-(D14-D15) -> 50829.34 | E16: =E13-(E14-E15) -> 22989.34 | F16: =F13-(F14-F15) -> 35773.34 | G16: =G13-(G14-G15) -> 78698.01 | H16: =H13-(H14-H15) -> 74765.01 | I16: =I13-(I14-I15) -> 105144 | J16: =J13-(J14-J15) -> 63186.62 | K16: =K13-(K14-K15) -> 48894.2

Sheet Datos Fuente
B2: Datos Fuente — Cifras Originales del Estado de Resultados del Cliente
B3: Valores de entrada (celdas en azul) tomados directamente del archivo original del cliente. No editar — las hojas siguientes calculan sobre esta base.
B6: Concepto | C6: Nov-24 | D6: Dic-24 | E6: Ene-25 | F6: Feb-25 | G6: Mar-25 | H6: Abr-25 | I6: May-25 | J6: Jun-25 | K6: Jul-25 | L6: Ago-25 | M6: Sep-25 | N6: Oct-25 | O6: Nov-25 | P6: Dic-25 | Q6: Ene-26 | R6: Feb-26 | S6: Mar-26 | T6: Abr-26 | U6: May-26
B7: INGRESOS (sección) | C7: 0 | D7: 0 | E7: 0 | F7: 0 | G7: 0 | H7: 0 | I7: 0 | J7: 0 | K7: 0 | L7: 0 | M7: 0 | N7: 0 | O7: 0 | P7: 0 | Q7: 0 | R7: 0 | S7: 0 | T7: 0 | U7: 0
B8: Cancha | C8: 81741.85 | D8: 95495 | E8: 99567 | F8: 93620 | G8: 109082 | H8: 120527 | I8: 101404 | J8: 113871 | K8: 120065 | L8: 120267 | M8: 110453 | N8: 119750 | O8: 101884 | P8: 106978 | Q8: 120974.57 | R8: 100805 | S8: 119721.28 | T8: 122406.17 | U8: 102242
B9: Clases | C9: 17000 | D9: 2400 | E9: 13200 | F9: 31200 | G9: 26500 | H9: 30400 | I9: 26600 | J9: 36350 | K9: 50500 | L9: 18500 | M9: 48025 | N9: 40225 | O9: 43600 | P9: 40400 | Q9: 49125 | R9: 46350 | S9: 51125 | T9: 61000 | U9: 63700
B10: Bebidas | C10: 11020 | D10: 11936 | E10: 10435 | F10: 12510 | G10: 15730 | H10: 15405 | I10: 15320 | J10: 12260 | K10: 18330 | L10: 16475 | M10: 14460 | N10: 17785 | O10: 16485 | P10: 15440 | Q10: 15879 | R10: 14924.13 | S10: 19021.92 | T10: 20212.22 | U10: 19507.36
B11: Pelotas | C11: 6247 | D11: 5237 | E11: 3918 | F11: 3146 | G11: 9858 | H11: 12248 | I11: 7884 | J11: 12870 | K11: 11740 | L11: 12154 | M11: 14504 | N11: 12055 | O11: 12605 | P11: 11500 | Q11: 13541.72 | R11: 11785.99 | S11: 13550 | T11: 12321.22 | U11: 10159.64
B12: Cafetería | C12: 0 | D12: 0 | E12: 0 | F12: 5905 | G12: 6950 | H12: 6010 | I12: 7860 | J12: 10720 | K12: 13740 | L12: 10350 | M12: 12565 | N12: 11405 | O12: 9780 | P12: 10875 | Q12: 12011.78 | R12: 8140 | S12: 11242 | T12: 7516.98 | U12: 6024.64
B13: Botana | C13: 2585 | D13: 2875 | E13: 2750 | F13: 2845 | G13: 3160 | H13: 3350 | I13: 3675 | J13: 4775 | K13: 7865 | L13: 7495 | M13: 6535 | N13: 9520 | O13: 7945 | P13: 6595 | Q13: 8200 | R13: 6583.16 | S13: 6571.77 | T13: 5980.04 | U13: 4197.43
B14: Grips y Palas | C14: 2525 | D14: 4385 | E14: 2180 | F14: 3715 | G14: 3915 | H14: 4120 | I14: 2830 | J14: 2530 | K14: 5080 | L14: 4385 | M14: 2215 | N14: 6740 | O14: 2760 | P14: 3105 | Q14: 3450 | R14: 2150.71 | S14: 2305 | T14: 3065 | U14: 1965
B15: Sacos | C15: 0 | D15: 0 | E15: 0 | F15: 0 | G15: 0 | H15: 0 | I15: 0 | J15: 0 | K15: 0 | L15: 0 | M15: 0 | N15: 0 | O15: 0 | P15: 0 | Q15: 700 | R15: 2100 | S15: 0 | T15: 350 | U15: 0
B16: Fondo Apapacho (ingreso) | C16: 0 | D16: 0 | E16: 1110 | F16: 0 | G16: 300 | H16: 0 | I16: 0 | J16: 0 | K16: 0 | L16: 50 | M16: 0 | N16: 750 | O16: 1050 | P16: 700 | Q16: 950 | R16: 400 | S16: 550 | T16: 600 | U16: 900
B18: EGRESOS (sección) | C18: 0 | D18: 0 | E18: 0 | F18: 0 | G18: 0 | H18: 0 | I18: 0 | J18: 0 | K18: 0 | L18: 0 | M18: 0 | N18: 0 | O18: 0 | P18: 0 | Q18: 0 | R18: 0 | S18: 0 | T18: 0 | U18: 0
B19: Abogado | C19: 0 | D19: 0 | E19: 0 | F19: 0 | G19: 0 | H19: 0 | I19: 0 | J19: 0 | K19: 0 | L19: 0 | M19: 0 | N19: 0 | O19: 0 | P19: 0 | Q19: 65741.64 | R19: 9110 | S19: 0 | T19: 0 | U19: 0
... B42: Transporte TAG Gasolina (personal) | C42: 2482 | D42: 3964 | E42: 700 | F42: 1500 | G42: 2158 | H42: 1500 | I42: 1619 | J42: 4428 | K42: 35552 | L42: 7225 | M42: 5995 | N42: 10300 | O42: 3378 | P42: 15165 | Q42: 0 | R42: 0 | S42: 0 | T42: 0 | U42: 0
